resmlp_flax/__init__.py
resmlp_flax/model.py
resmlp_flax/utils.py
resmlp_flax-0.0.1.dist-info/LICENSE
resmlp_flax-0.0.1.dist-info/METADATA
resmlp_flax-0.0.1.dist-info/WHEEL
resmlp_flax-0.0.1.dist-info/top_level.txt
resmlp_flax-0.0.1.dist-info/zip-safe
resmlp_flax-0.0.1.dist-info/RECORD
