Metadata-Version: 2.1
Name: resmlp-flax
Version: 0.0.1
Summary: Minimal Flax implementation of ResMLP: Feedforward networks for image classification with data-efficient training
Home-page: https://github.com/SauravMaheshkar/ResMLP-Flax
Author: Saurav Maheshkar
Author-email: sauravvmaheshkar@gmail.com
License: MIT
Platform: UNKNOWN
Requires-Dist: flax
Requires-Dist: jax
